MANIFEST.in
setup.py
src/verst/__init__.py
src/verst.pants.s3cache.egg-info/PKG-INFO
src/verst.pants.s3cache.egg-info/SOURCES.txt
src/verst.pants.s3cache.egg-info/dependency_links.txt
src/verst.pants.s3cache.egg-info/entry_points.txt
src/verst.pants.s3cache.egg-info/namespace_packages.txt
src/verst.pants.s3cache.egg-info/requires.txt
src/verst.pants.s3cache.egg-info/top_level.txt
src/verst.pants.s3cache.egg-info/zip-safe
src/verst/pants/__init__.py
src/verst/pants/s3cache/__init__.py
src/verst/pants/s3cache/cache_setup.py
src/verst/pants/s3cache/register.py
src/verst/pants/s3cache/s3cache.py