Metadata-Version: 1.1
Name: verst.pants.s3cache
Version: 1.2.0
Summary: An S3 caching backend for pants artifact cache
Home-page: https://github.com/toddgardner/pants-plugins
Author: Todd Gardner
Author-email: todd.gardner@gmail.com
License: MIT
Platform: UNKNOWN
Classifier: Intended Audience :: Developers
Classifier: License :: OSI Approved :: MIT License
Classifier: Operating System :: MacOS :: MacOS X
Classifier: Operating System :: POSIX :: Linux
Classifier: Programming Language :: Python
Classifier: Topic :: Software Development :: Build Tools
